region_estimators/__init__.py
region_estimators/concentric_regions_estimator.py
region_estimators/distance_simple_estimator.py
region_estimators/estimation_data.py
region_estimators/region_estimator.py
region_estimators/region_estimator_factory.py
test/__init__.py
test/test_concentric_regions_estimator.py
test/test_distance_estimator.py
test/test_estimation_data.py
test/test_region_estimator.py
test/test_region_estimator_factory.py
test/test_regions_concentric_regions_edge_cases.py
test/test_regions_distance_edge_cases.py
test/bespoke/__init__.py
test/bespoke/xtest_bespoke_concentric_regions_estimator.py
region_estimators-1.2.0.dist-info/LICENSE
region_estimators-1.2.0.dist-info/METADATA
region_estimators-1.2.0.dist-info/WHEEL
region_estimators-1.2.0.dist-info/top_level.txt
region_estimators-1.2.0.dist-info/RECORD
