Metadata-Version: 2.1
Name: region_estimators
Version: 1.2.0
Summary: Make estimations for geographic regions, based on actual data (e.g. from sensors)
Home-page: https://github.com/UoMResearchIT/region-estimators
Author: Ann Gledson
Author-email: ann.gledson@manchester.ac.uk
License: UNKNOWN
Platform: UNKNOWN
Classifier: Programming Language :: Python :: 3.6
Classifier: License :: OSI Approved :: MIT License
Classifier: Operating System :: OS Independent
Requires-Python: >=3.5
License-File: LICENSE
